aerospike_provider/__init__.py
aerospike_provider/hooks/__init__.py
aerospike_provider/hooks/aerospike.py
aerospike_provider/operators/__init__.py
aerospike_provider/operators/aerospike.py
aerospike_provider/sensors/__init__.py
aerospike_provider/sensors/aerospike.py
tests/__init__.py
tests/hooks/__init__.py
tests/hooks/test_aerospike.py
tests/operators/__init__.py
tests/operators/test_aerospike.py
tests/sensors/__init__.py
tests/sensors/test_aerospike.py
airflow_provider_aerospike-0.0.1.dist-info/LICENSE
airflow_provider_aerospike-0.0.1.dist-info/METADATA
airflow_provider_aerospike-0.0.1.dist-info/WHEEL
airflow_provider_aerospike-0.0.1.dist-info/entry_points.txt
airflow_provider_aerospike-0.0.1.dist-info/top_level.txt
airflow_provider_aerospike-0.0.1.dist-info/RECORD
