Metadata-Version: 2.1
Name: airflow_provider_aerospike
Version: 0.0.1
Summary: A Aerospike provider for Apache Airflow
Home-page: https://github.com/eldar-eln-bigabid/airflow-aerospike-provider
Author: Eldar Elnekave
License: Apache-2.0
Requires-Python: >=3.8
License-File: LICENSE
Requires-Dist: apache-airflow >=2.2.0
Requires-Dist: aerospike ==14.0.0
Provides-Extra: dev
Requires-Dist: pre-commit ==2.15.0 ; extra == 'dev'
Requires-Dist: mypy ==1.8.0 ; extra == 'dev'
